httk/__init__.py
httk/__main__.py
httk/cli.py
httk/distdata.py
httk/httk.cfg
httk/versioning.py
httk/analysis/__init__.py
httk/analysis/matsci/__init__.py
httk/analysis/matsci/phasediagram.py
httk/analysis/matsci/vis/__init__.py
httk/analysis/matsci/vis/matplotlibphasediagramvisualizer.py
httk/analysis/matsci/vis/phasediagramvisualizerplugin.py
httk/atomistic/__init__.py
httk/atomistic/assignment.py
httk/atomistic/assignments.py
httk/atomistic/cell.py
httk/atomistic/cellshape.py
httk/atomistic/cellutils.py
httk/atomistic/cli.py
httk/atomistic/compound.py
httk/atomistic/formulautils.py
httk/atomistic/representativesites.py
httk/atomistic/representativestructure.py
httk/atomistic/siteassignment.py
httk/atomistic/sites.py
httk/atomistic/sitesutils.py
httk/atomistic/spacegroup.py
httk/atomistic/spacegrouputils.pkl
httk/atomistic/spacegrouputils.py
httk/atomistic/structure.py
httk/atomistic/structurephasediagram.py
httk/atomistic/structureutils.py
httk/atomistic/supercellutils.py
httk/atomistic/unitcellsites.py
httk/atomistic/unitcellstructure.py
httk/atomistic/atomisticio/__init__.py
httk/atomistic/atomisticio/structure_cif_io.py
httk/atomistic/atomisticio/structure_io.py
httk/atomistic/atomisticio/structureioplugin.py
httk/atomistic/data/__init__.py
httk/atomistic/data/periodictable.py
httk/atomistic/data/spacegroups.py
httk/atomistic/results/__init__.py
httk/atomistic/results/relaxedcellresult.py
httk/atomistic/results/totalenergyresult.py
httk/atomistic/vis/__init__.py
httk/atomistic/vis/asestructurevisualizer.py
httk/atomistic/vis/jmolstructurevisualizer.py
httk/atomistic/vis/structurephasediagramvisualizerplugin.py
httk/atomistic/vis/structurevisualizerplugin.py
httk/config/__init__.py
httk/config/config.py
httk/core/__init__.py
httk/core/_basic_py2.py
httk/core/_basic_py3.py
httk/core/_ed25519_orig.py
httk/core/basic.py
httk/core/citation.py
httk/core/code.py
httk/core/computation.py
httk/core/console.py
httk/core/crypto.py
httk/core/ed25519.py
httk-1.2.0.dist-info/LICENSE.txt
httk-1.2.0.dist-info/METADATA
httk-1.2.0.dist-info/WHEEL
httk-1.2.0.dist-info/entry_points.txt
httk-1.2.0.dist-info/top_level.txt
httk-1.2.0.dist-info/RECORD
