Metadata-Version: 2.1
Name: httk
Version: 1.2.0
Summary: The high-thoughput toolkit: workflow, project management, storage, and data analysis for large-scale computational projects
Home-page: https://httk.openmaterialsdb.se
Author: Rickard Armiento, et al.
Author-email: UNKNOWN
License: UNKNOWN
Keywords: high-throughput workflow project-management storage database analysis computational atomistic
Platform: UNKNOWN
Classifier: Development Status :: 4 - Beta
Classifier: Intended Audience :: Science/Research
Classifier: Topic :: Software Development :: Libraries
Classifier: License :: OSI Approved :: GNU Affero General Public License v3 or later (AGPLv3+)
Classifier: Programming Language :: Python :: 2
Classifier: Programming Language :: Python :: 2.7
